paramclasses/__init__.py
paramclasses/paramclasses.py
paramclasses/py.typed
paramclasses-0.4.2.dist-info/METADATA
paramclasses-0.4.2.dist-info/WHEEL
paramclasses-0.4.2.dist-info/licenses/LICENSE
paramclasses-0.4.2.dist-info/RECORD
