Metadata-Version: 2.4
Name: paramclasses
Version: 0.4.2
Summary: Parameter-holding classes with robust subclassing protection
Project-URL: Homepage, https://github.com/eliegoudout/paramclasses
Project-URL: Issues, https://github.com/eliegoudout/paramclasses/issues
Author-email: Élie Goudout <eliegoudout@hotmail.com>
License: MIT License
License-File: LICENSE
Classifier: Development Status :: 4 - Beta
Classifier: Framework :: Pytest
Classifier: Intended Audience :: Developers
Classifier: License :: OSI Approved :: MIT License
Classifier: Natural Language :: English
Classifier: Operating System :: OS Independent
Classifier: Programming Language :: Python :: 3
Classifier: Programming Language :: Python :: 3.10
Classifier: Programming Language :: Python :: 3.11
Classifier: Programming Language :: Python :: 3.12
Classifier: Programming Language :: Python :: 3.13
Classifier: Programming Language :: Python :: 3.14
Classifier: Typing :: Typed
Requires-Python: <3.15,>=3.10
